acb_tools/__init__.py
acb_tools/assessment_tool.cpython-312-x86_64-linux-gnu.so
acb_tools/run_command.cpython-312-x86_64-linux-gnu.so
acb_tools/vis_sim_acb.cpython-312-x86_64-linux-gnu.so
acb_tools/simulator/__init__.py
acb_tools/simulator/analyze_sim_result.cpython-312-x86_64-linux-gnu.so
acb_tools/simulator/run_simulation.cpython-312-x86_64-linux-gnu.so
acb_tools/simulator/sim_acb.cpython-312-x86_64-linux-gnu.so
acb_tools/simulator/simulator.cpython-312-x86_64-linux-gnu.so
acb_tools/simulator/simulator_config.cpython-312-x86_64-linux-gnu.so
acb_tools/visualizer/__init__.py
adaptive_gpu_allocator/__init__.py
adaptive_gpu_allocator/adaptive_gpu_allocator.cpython-312-x86_64-linux-gnu.so
adaptive_gpu_allocator/agarun.cpython-312-x86_64-linux-gnu.so
adaptive_gpu_allocator/env.cpython-312-x86_64-linux-gnu.so
adaptive_gpu_allocator/history.cpython-312-x86_64-linux-gnu.so
adaptive_gpu_allocator/lightning.cpython-312-x86_64-linux-gnu.so
adaptive_gpu_allocator/metrics.cpython-312-x86_64-linux-gnu.so
adaptive_gpu_allocator/noop.cpython-312-x86_64-linux-gnu.so
adaptive_gpu_allocator/noop_pytorch_automatic.cpython-312-x86_64-linux-gnu.so
adaptive_gpu_allocator/pytorch.cpython-312-x86_64-linux-gnu.so
adaptive_gpu_allocator/pytorch_automatic.cpython-312-x86_64-linux-gnu.so
adaptive_gpu_allocator/pytorch_automatic_main.py
adaptive_gpu_allocator/pytorch_ddp.cpython-312-x86_64-linux-gnu.so
adaptive_gpu_allocator/pytorch_tensor_trace.cpython-312-x86_64-linux-gnu.so
adaptive_gpu_allocator/tensorflow.cpython-312-x86_64-linux-gnu.so
gpu_assigner/__init__.py
gpu_assigner/cli.cpython-312-x86_64-linux-gnu.so
gpu_assigner/client.cpython-312-x86_64-linux-gnu.so
gpu_assigner/config.cpython-312-x86_64-linux-gnu.so
gpu_assigner/device_finder.cpython-312-x86_64-linux-gnu.so
gpu_assigner/license_manager.cpython-312-x86_64-linux-gnu.so
gpu_assigner/proxy_helper.cpython-312-x86_64-linux-gnu.so
gpu_assigner/scheduler.cpython-312-x86_64-linux-gnu.so
ai_computing_broker-1.0.1.dist-info/METADATA
ai_computing_broker-1.0.1.dist-info/WHEEL
ai_computing_broker-1.0.1.dist-info/entry_points.txt
ai_computing_broker-1.0.1.dist-info/top_level.txt
ai_computing_broker-1.0.1.dist-info/RECORD
