Metadata-Version: 2.4
Name: ai-computing-broker
Version: 1.0.1
Platform: linux_x86_64
Requires-Dist: grpcio!=1.68.1
Requires-Dist: grpcio-tools!=1.68.1
Requires-Dist: numpy
Requires-Dist: nvidia-ml-py
Requires-Dist: optree
Requires-Dist: scipy
Requires-Dist: toml
Requires-Dist: cryptography>=41.0.0
Requires-Dist: requests
Requires-Dist: typing-extensions
Dynamic: description
Dynamic: description-content-type
Dynamic: platform
Dynamic: requires-dist
